wagtailnews/__init__.py
wagtailnews/apps.py
wagtailnews/blocks.py
wagtailnews/conf.py
wagtailnews/decorators.py
wagtailnews/deprecation.py
wagtailnews/edit_handlers.py
wagtailnews/feeds.py
wagtailnews/forms.py
wagtailnews/menu.py
wagtailnews/models.py
wagtailnews/permissions.py
wagtailnews/urls.py
wagtailnews/version.py
wagtailnews/wagtail_hooks.py
wagtailnews/widgets.py
wagtailnews/static/js/news_chooser.js
wagtailnews/templates/wagtailnews/choose.html
wagtailnews/templates/wagtailnews/create.html
wagtailnews/templates/wagtailnews/delete.html
wagtailnews/templates/wagtailnews/edit.html
wagtailnews/templates/wagtailnews/index.html
wagtailnews/templates/wagtailnews/newsitem_list.html
wagtailnews/templates/wagtailnews/search.html
wagtailnews/templates/wagtailnews/search_results.html
wagtailnews/templates/wagtailnews/unpublish.html
wagtailnews/templates/wagtailnews/chooser/choose.js
wagtailnews/templates/wagtailnews/chooser/chooser.html
wagtailnews/templates/wagtailnews/chooser/chosen.js
wagtailnews/templates/wagtailnews/chooser/list.html
wagtailnews/templates/wagtailnews/chooser/search_results.html
wagtailnews/templates/wagtailnews/permissions/includes/newsitem_permissions_formset.html
wagtailnews/templates/wagtailnews/widgets/news_chooser.html
wagtailnews/templatetags/__init__.py
wagtailnews/templatetags/wagtailnews_admin_tags.py
wagtailnews/views/__init__.py
wagtailnews/views/chooser.py
wagtailnews/views/editor.py
wagtailnews_collection-0.17.11.dist-info/DESCRIPTION.rst
wagtailnews_collection-0.17.11.dist-info/METADATA
wagtailnews_collection-0.17.11.dist-info/RECORD
wagtailnews_collection-0.17.11.dist-info/WHEEL
wagtailnews_collection-0.17.11.dist-info/metadata.json
wagtailnews_collection-0.17.11.dist-info/top_level.txt
