Metadata-Version: 2.0
Name: wagtailnews-collection
Version: 0.17.11
Summary: News / blog plugin for the Wagtail CMS, but with news items belonging to collections, enforcing permissions
Home-page: https://github.com/taywee/wagtailnews-collection/
Author: Taylor C. Richberger
Author-email: tcr@absolute-performance.com
License: BSD License
Platform: UNKNOWN
Classifier: Environment :: Web Environment
Classifier: Intended Audience :: Developers
Classifier: Operating System :: OS Independent
Classifier: Programming Language :: Python
Classifier: Programming Language :: Python :: 3
Classifier: Framework :: Django
Classifier: License :: OSI Approved :: BSD License
Requires-Dist: wagtail (>=1.5)
Provides-Extra: docs
Requires-Dist: Sphinx (>=1.4.6); extra == 'docs'
Requires-Dist: sphinx-autobuild (>=0.5.2); extra == 'docs'
Requires-Dist: sphinx-rtd-theme (>=0.1.8); extra == 'docs'
Requires-Dist: sphinxcontrib-spelling (==2.1.1); extra == 'docs'
Requires-Dist: pyenchant (==1.6.6); extra == 'docs'
